youtubeinsights_mcp_server/__init__.py
youtubeinsights_mcp_server/server.py
youtubeinsights_mcp_server-0.1.2.dist-info/METADATA
youtubeinsights_mcp_server-0.1.2.dist-info/WHEEL
youtubeinsights_mcp_server-0.1.2.dist-info/entry_points.txt
youtubeinsights_mcp_server-0.1.2.dist-info/licenses/LICENSE
youtubeinsights_mcp_server-0.1.2.dist-info/RECORD
